FSM/VendingFSM.v
module vending_fsm (
    input  clk,
    input  rst_n,        // async reset
    input  coin5,        // 投入 5 元 (pulse)
    input  coin10,       // 投入 10 元 (pulse)
    output reg vend,     // 出貨
    output reg change    // 找 5 元
);

    localparam S_0 = 3'b000, S_5 = 3'b001, S_10 = 3'b010, S_VEND = 3'b011, S_VEND_CHANGE = 3'b100;

    reg [2:0] state, next_state;

    // State
    always @(posedge clk or negedge rst_n) begin
        if (!rst_n) 
            state <= S_0;
        else 
            state <= next_state;
    end

    always @(*) begin
        next_state = state;
        vend = 1'b0;
        change = 1'b0;
        case (state)
            S_0: begin
                if (coin5) next_state = S_5;
                else if (coin10) next_state = S_10;
            end
            S_5: begin
                if (coin5) next_state = S_10;
                else if (coin10) next_state = S_VEND;
            end
            S_10: begin
                if (coin5) next_state = S_VEND;
                else if (coin10) next_state = S_VEND_CHANGE;
            end
            S_VEND: begin
                vend = 1'b1;
                next_state = S_0; // 出貨後回到初始狀態
            end
            S_VEND_CHANGE: begin
                vend = 1'b1;
                change = 1'b1;
                next_state = S_0; // 出貨後回到初始狀態
            end
            default: next_state = S_0; // 異常恢復
        endcase
    end
endmodule

FSM/vending_fsm_tb.v
`timescale 1ns/1ps

module vending_fsm_tb;
  reg clk;
  reg rst_n;
  reg coin5, coin10;
  wire vend, change;

  integer pass_count, fail_count;

  vending_fsm dut (
    .clk(clk),
    .rst_n(rst_n),
    .coin5(coin5),
    .coin10(coin10),
    .vend(vend),
    .change(change)
  );

    initial clk = 0;
    always #5 clk = ~clk; // 100MHz clock

    // 投幣 task：在 negedge 拉高，下一個 negedge 拉低，確保剛好 1 cycle
    task pulse_coin5;
    begin
        @(negedge clk); coin5 = 1;
        @(negedge clk); coin5 = 0;
    end
    endtask

    task pulse_coin10;
    begin
        @(negedge clk); coin10 = 1;
        @(negedge clk); coin10 = 0;
    end
    endtask

    // 等待 N 個 clock cycle（用 negedge 對齊）
    task wait_cycles(input integer n);
        integer i;
    begin
        for (i = 0; i < n; i = i + 1)
            @(negedge clk);
    end
    endtask

    // 驗證 task：檢查 vend/change 是否符合預期，且只維持 1 cycle
    task check_output(
        input exp_vend,
        input exp_change,
        input [79:0] test_name  // 10 chars max
    );
    begin
        // pulse task 回傳時已在 negedge，state 已在上一個 posedge 更新，
        // 組合輸出已有效，直接取樣即可
        if (vend !== exp_vend || change !== exp_change) begin
            $display("FAIL %0s: vend=%b change=%b (expected vend=%b change=%b)",
                     test_name, vend, change, exp_vend, exp_change);
            fail_count = fail_count + 1;
        end else begin
            $display("PASS %0s: vend=%b change=%b", test_name, vend, change);
            pass_count = pass_count + 1;
        end

        // 確認下一個 cycle 輸出歸零（只維持 1 cycle）
        @(posedge clk);
        @(negedge clk);
        if (vend !== 1'b0 || change !== 1'b0) begin
            $display("FAIL %0s: output not cleared after 1 cycle (vend=%b change=%b)",
                     test_name, vend, change);
            fail_count = fail_count + 1;
        end
    end
    endtask

    initial begin
        $dumpfile("vending_fsm_tb.vcd");
        $dumpvars(0, vending_fsm_tb);

        pass_count = 0;
        fail_count = 0;

        // Reset
        rst_n = 0; coin5 = 0; coin10 = 0;
        wait_cycles(3);
        rst_n = 1;
        wait_cycles(1);

        // ============================================================
        // Case 1: 10 + 5 = 15 → vend only
        // ============================================================
        $display("\n--- Case 1: 10 + 5 ---");
        pulse_coin10;       // 累積 10 元
        pulse_coin5;        // 累積 15 元 → 進入 S_VEND
        check_output(1'b1, 1'b0, "Case1");

        wait_cycles(2);

        // ============================================================
        // Case 2: 5 + 10 = 15 → vend only
        // ============================================================
        $display("\n--- Case 2: 5 + 10 ---");
        pulse_coin5;        // 累積 5 元
        pulse_coin10;       // 累積 15 元 → 進入 S_VEND
        check_output(1'b1, 1'b0, "Case2");

        wait_cycles(2);

        // ============================================================
        // Case 3: 10 + 10 = 20 → vend + change
        // ============================================================
        $display("\n--- Case 3: 10 + 10 ---");
        pulse_coin10;       // 累積 10 元
        pulse_coin10;       // 累積 20 元 → 進入 S_VEND_CHANGE
        check_output(1'b1, 1'b1, "Case3");

        wait_cycles(2);

        // ============================================================
        // Case 4: 5 + 5 + 5 = 15 → vend only
        // ============================================================
        $display("\n--- Case 4: 5 + 5 + 5 ---");
        pulse_coin5;        // 累積 5 元
        pulse_coin5;        // 累積 10 元
        pulse_coin5;        // 累積 15 元 → 進入 S_VEND
        check_output(1'b1, 1'b0, "Case4");

        wait_cycles(2);

        // ============================================================
        // Case 5: 5 + 5 + 10 = 20 → vend + change
        // ============================================================
        $display("\n--- Case 5: 5 + 5 + 10 ---");
        pulse_coin5;        // 累積 5 元
        pulse_coin5;        // 累積 10 元
        pulse_coin10;       // 累積 20 元 → 進入 S_VEND_CHANGE
        check_output(1'b1, 1'b1, "Case5");

        wait_cycles(2);

        // ============================================================
        // Case 6: Reset 中途投幣後應歸零
        // ============================================================
        $display("\n--- Case 6: Reset mid-transaction ---");
        pulse_coin10;       // 累積 10 元
        @(negedge clk); rst_n = 0;  // 中途 reset
        wait_cycles(2);
        rst_n = 1;
        @(negedge clk);
        if (vend !== 1'b0 || change !== 1'b0) begin
            $display("FAIL Case6: outputs not zero after reset (vend=%b change=%b)",
                     vend, change);
            fail_count = fail_count + 1;
        end else begin
            $display("PASS Case6: reset clears state correctly");
            pass_count = pass_count + 1;
        end
        // 確認 reset 後仍能正常運作
        pulse_coin10;
        pulse_coin5;
        check_output(1'b1, 1'b0, "Case6b");

        // ============================================================
        // Summary
        // ============================================================
        $display("\n============================");
        $display("  Results: %0d PASS, %0d FAIL", pass_count, fail_count);
        $display("============================\n");

        if (fail_count == 0)
            $display("ALL TESTS PASSED!");
        else
            $display("SOME TESTS FAILED!");

        $finish;
    end

endmodule

FSM/vending_fsm_tb.vcd
$date
	Sun Feb 15 16:46:57 2026
$end
$version
	Icarus Verilog
$end
$timescale
	1ps
$end
$scope module vending_fsm_tb $end
$var wire 1 ! vend $end
$var wire 1 " change $end
$var reg 1 # clk $end
$var reg 1 $ coin10 $end
$var reg 1 % coin5 $end
$var reg 1 & rst_n $end
$var integer 32 ' fail_count [31:0] $end
$var integer 32 ( pass_count [31:0] $end
$scope module dut $end
$var wire 1 # clk $end
$var wire 1 $ coin10 $end
$var wire 1 % coin5 $end
$var wire 1 & rst_n $end
$var parameter 3 ) S_0 $end
$var parameter 3 * S_10 $end
$var parameter 3 + S_5 $end
$var parameter 3 , S_VEND $end
$var parameter 3 - S_VEND_CHANGE $end
$var reg 1 " change $end
$var reg 3 . next_state [2:0] $end
$var reg 3 / state [2:0] $end
$var reg 1 ! vend $end
$upscope $end
$scope task check_output $end
$var reg 1 0 exp_change $end
$var reg 1 1 exp_vend $end
$var reg 80 2 test_name [79:0] $end
$upscope $end
$scope task pulse_coin10 $end
$upscope $end
$scope task pulse_coin5 $end
$upscope $end
$scope task wait_cycles $end
$var integer 32 3 i [31:0] $end
$var integer 32 4 n [31:0] $end
$upscope $end
$upscope $end
$enddefinitions $end
$comment Show the parameter values. $end
$dumpall
b100 -
b11 ,
b1 +
b10 *
b0 )
$end
#0
$dumpvars
b11 4
b0 3
bx 2
x1
x0
b0 /
b0 .
b0 (
b0 '
0&
0%
0$
0#
0"
0!
$end
#5000
1#
#10000
b1 3
0#
#15000
1#
#20000
b10 3
0#
#25000
1#
#30000
b1 4
1&
b0 3
0#
#35000
1#
#40000
b1 3
0#
#45000
1#
#50000
b10 .
1$
0#
#55000
b100 .
b10 /
1#
#60000
b10 .
0$
0#
#65000
1#
#70000
b11 .
1%
0#
#75000
b0 .
1!
b11 /
1#
#80000
1!
b0 .
b1 (
b100001101100001011100110110010100110001 2
00
11
0%
0#
#85000
0!
b0 /
1#
#90000
b0 3
b10 4
0#
#95000
1#
#100000
b1 3
0#
#105000
1#
#110000
b10 3
0#
#115000
1#
#120000
b1 .
1%
0#
#125000
b10 .
b1 /
1#
#130000
b1 .
0%
0#
#135000
1#
#140000
b11 .
1$
0#
#145000
b0 .
1!
b11 /
1#
#150000
1!
b0 .
b10 (
b100001101100001011100110110010100110010 2
0$
0#
#155000
0!
b0 /
1#
#160000
b0 3
0#
#165000
1#
#170000
b1 3
0#
#175000
1#
#180000
b10 3
0#
#185000
1#
#190000
b10 .
1$
0#
#195000
b100 .
b10 /
1#
#200000
b10 .
0$
0#
#205000
1#
#210000
b100 .
1$
0#
#215000
b0 .
1"
1!
b100 /
1#
#220000
1"
1!
b0 .
b11 (
b100001101100001011100110110010100110011 2
10
0$
0#
#225000
0"
0!
b0 /
1#
#230000
b0 3
0#
#235000
1#
#240000
b1 3
0#
#245000
1#
#250000
b10 3
0#
#255000
1#
#260000
b1 .
1%
0#
#265000
b10 .
b1 /
1#
#270000
b1 .
0%
0#
#275000
1#
#280000
b10 .
1%
0#
#285000
b11 .
b10 /
1#
#290000
b10 .
0%
0#
#295000
1#
#300000
b11 .
1%
0#
#305000
b0 .
1!
b11 /
1#
#310000
1!
b0 .
b100 (
b100001101100001011100110110010100110100 2
00
0%
0#
#315000
0!
b0 /
1#
#320000
b0 3
0#
#325000
1#
#330000
b1 3
0#
#335000
1#
#340000
b10 3
0#
#345000
1#
#350000
b1 .
1%
0#
#355000
b10 .
b1 /
1#
#360000
b1 .
0%
0#
#365000
1#
#370000
b10 .
1%
0#
#375000
b11 .
b10 /
1#
#380000
b10 .
0%
0#
#385000
1#
#390000
b100 .
1$
0#
#395000
b0 .
1"
1!
b100 /
1#
#400000
1"
1!
b0 .
b101 (
b100001101100001011100110110010100110101 2
10
0$
0#
#405000
0"
0!
b0 /
1#
#410000
b0 3
0#
#415000
1#
#420000
b1 3
0#
#425000
1#
#430000
b10 3
0#
#435000
1#
#440000
b10 .
1$
0#
#445000
b100 .
b10 /
1#
#450000
b10 .
0$
0#
#455000
1#
#460000
b0 .
b0 /
b0 3
0&
0#
#465000
1#
#470000
b1 3
0#
#475000
1#
#480000
1&
b10 3
0#
#485000
1#
#490000
b110 (
0#
#495000
1#
#500000
b10 .
1$
0#
#505000
b100 .
b10 /
1#
#510000
b10 .
0$
0#
#515000
1#
#520000
b11 .
1%
0#
#525000
b0 .
1!
b11 /
1#
#530000
1!
b0 .
b111 (
b10000110110000101110011011001010011011001100010 2
00
0%
0#
#535000
0!
b0 /
1#
